{
    "get_ep_activities_calories_intraday_by_date": [
        {
            "date": "2025-10-25",
            "status": "success",
            "timestamp": "2025-10-25-21:00:49"
        }
    ],
    "get_ep_activities_distance_intraday_by_date": [
        {
            "date": "2025-10-25",
            "status": "success",
            "timestamp": "2025-10-25-21:00:50"
        }
    ],
    "get_ep_activities_elevation_intraday_by_date": [
        {
            "date": "2025-10-25",
            "status": "success",
            "timestamp": "2025-10-25-21:00:51"
        }
    ],
    "get_ep_activities_floors_intraday_by_date": [
        {
            "date": "2025-10-25",
            "status": "success",
            "timestamp": "2025-10-25-21:00:52"
        }
    ],
    "get_ep_activities_steps_intraday_by_date": [
        {
            "date": "2025-10-25",
            "status": "success",
            "timestamp": "2025-10-25-21:00:53"
        }
    ],
    "get_ep_br_intraday_by_interval": [
        {
            "date": "2025-10-25",
            "status": "success",
            "timestamp": "2025-10-25-21:00:59"
        }
    ],
    "get_ep_ecg_intraday_by_date": [
        {
            "date": "2025-10-25",
            "status": "success",
            "timestamp": "2025-10-25-21:00:54"
        }
    ],
    "get_ep_hr_intraday_by_date": [
        {
            "date": "2025-10-25",
            "status": "success",
            "timestamp": "2025-10-25-21:00:58"
        }
    ],
    "get_ep_hrv_intraday_by_interval": [
        {
            "date": "2025-10-25",
            "status": "success",
            "timestamp": "2025-10-25-21:01:01"
        }
    ],
    "get_ep_sleeplog_by_interval": [
        {
            "date": "2025-10-25",
            "status": "success",
            "timestamp": "2025-10-25-21:01:04"
        }
    ],
    "get_ep_spo2_intraday_by_interval": [
        {
            "date": "2025-10-25",
            "status": "success",
            "timestamp": "2025-10-25-21:01:06"
        }
    ],
    "get_ep_tempskin_by_date": [
        {
            "date": "2025-10-25",
            "status": "success",
            "timestamp": "2025-10-25-21:01:11"
        }
    ],
    "get_ep_vo2max_intraday_by_interval": [
        {
            "date": "2025-10-25",
            "status": "success",
            "timestamp": "2025-10-25-21:01:09"
        }
    ]
}